yfinance_ez/__init__.py
yfinance_ez/base.py
yfinance_ez/constants.py
yfinance_ez/ticker.py
yfinance_ez/utils.py
yfinance_ez/tests/__init__.py
yfinance_ez/tests/conftest.py
yfinance_ez/tests/test_base.py
yfinance_ez-0.5.6.dist-info/LICENSE.txt
yfinance_ez-0.5.6.dist-info/METADATA
yfinance_ez-0.5.6.dist-info/WHEEL
yfinance_ez-0.5.6.dist-info/entry_points.txt
yfinance_ez-0.5.6.dist-info/top_level.txt
yfinance_ez-0.5.6.dist-info/RECORD
