Metadata-Version: 2.1
Name: yfinance-ez
Version: 0.5.6
Summary: Yahoo! Finance market data downloader
Home-page: https://github.com/eschiff/yfinance_ez
Author: Ezra Schiff
Author-email: ezra.schiff@gmail.com
License: Apache
Keywords: pandas,yahoo finance,pandas datareader
Platform: any
Classifier: License :: OSI Approved :: Apache Software License
Classifier: Development Status :: 4 - Beta
Classifier: Operating System :: OS Independent
Classifier: Intended Audience :: Developers
Classifier: Topic :: Office/Business :: Financial
Classifier: Topic :: Office/Business :: Financial :: Investment
Classifier: Topic :: Scientific/Engineering :: Interface Engine/Protocol Translator
Classifier: Topic :: Software Development :: Libraries
Classifier: Topic :: Software Development :: Libraries :: Python Modules
Classifier: Programming Language :: Python :: 3.5
Classifier: Programming Language :: Python :: 3.6
Classifier: Programming Language :: Python :: 3.7
Requires-Python: >=3.6
License-File: LICENSE.txt
Requires-Dist: pandas (>=0.24)
Requires-Dist: numpy (>=1.15)
Requires-Dist: requests (>=2.20)
